aipatch/__init__.py
aipatch/main.py
aipatch/prelude.py
aipatch-0.1.17.dist-info/licenses/LICENSE
aipatch-0.1.17.dist-info/METADATA
aipatch-0.1.17.dist-info/WHEEL
aipatch-0.1.17.dist-info/entry_points.txt
aipatch-0.1.17.dist-info/top_level.txt
aipatch-0.1.17.dist-info/RECORD
