Metadata-Version: 2.4
Name: aipatch
Version: 0.1.17
Summary: CLI tool for gathering file context and applying LLM patches
License-Expression: LicenseRef-FRL
Project-URL: Repository, https://github.com/bendaydots/aipatch
Requires-Python: >=3.7
License-File: LICENSE
Requires-Dist: pyperclip
Dynamic: license-file
